gpflib/BCCconfig.txt
gpflib/GPF1.py
gpflib/GPF2.py
gpflib/GPFconfig.txt
gpflib/Parser.lua
gpflib/Segment.dat
gpflib/__init__.py
gpflib/__version__.py
gpflib/bcclib.dll
gpflib/gpf0.py
gpflib/gpf_Test.py
gpflib/gpflib.dll
gpflib/gpflib.py
gpflib/idxPOS.dat
gpflib/libbcclib.dylib
gpflib/libbcclib.so
gpflib/libgpflib.dylib
gpflib/libgpflib.so
gpflib/Graph/Pathplan.dll
gpflib/Graph/cdt.dll
gpflib/Graph/cgraph.dll
gpflib/Graph/config6
gpflib/Graph/dot.exe
gpflib/Graph/fontconfig.dll
gpflib/Graph/fontconfig_fix.dll
gpflib/Graph/freetype6.dll
gpflib/Graph/gvc.dll
gpflib/Graph/gvplugin_core.dll
gpflib/Graph/gvplugin_dot_layout.dll
gpflib/Graph/gvplugin_gd.dll
gpflib/Graph/gvplugin_pango.dll
gpflib/Graph/iconv.dll
gpflib/Graph/intl.dll
gpflib/Graph/jpeg62.dll
gpflib/Graph/libcairo-2.dll
gpflib/Graph/libexpat-1.dll
gpflib/Graph/libexpat.dll
gpflib/Graph/libfontconfig-1.dll
gpflib/Graph/libfreetype-6.dll
gpflib/Graph/libgdk_pixbuf-2.0-0.dll
gpflib/Graph/libglade-2.0-0.dll
gpflib/Graph/libglib-2.0-0.dll
gpflib/Graph/libgmodule-2.0-0.dll
gpflib/Graph/libgobject-2.0-0.dll
gpflib/Graph/libgthread-2.0-0.dll
gpflib/Graph/libgtkglext-win32-1.0-0.dll
gpflib/Graph/libpango-1.0-0.dll
gpflib/Graph/libpangocairo-1.0-0.dll
gpflib/Graph/libpangoft2-1.0-0.dll
gpflib/Graph/libpangowin32-1.0-0.dll
gpflib/Graph/libpng14-14.dll
gpflib/Graph/librsvg-2-2.dll
gpflib/Graph/libxml2.dll
gpflib/Graph/ltdl.dll
gpflib/Graph/zlib1.dll
gpflib-3.1.25.dist-info/licenses/LICENSE
gpflib-3.1.25.dist-info/METADATA
gpflib-3.1.25.dist-info/WHEEL
gpflib-3.1.25.dist-info/top_level.txt
gpflib-3.1.25.dist-info/RECORD
