Metadata-Version: 2.4
Name: gpflib
Version: 3.1.25
Summary: Grid-based Parsing Framework
Author: endongxun
Author-email: edxun@126.com
License: MIT
Classifier: Development Status :: 5 - Production/Stable
Classifier: Operating System :: Microsoft :: Windows
Classifier: Operating System :: POSIX :: Linux
Classifier: Intended Audience :: Developers
Classifier: Programming Language :: Python :: 3
Requires-Python: >=3.6
License-File: LICENSE
Requires-Dist: pywin32; platform_system == "Windows"
Requires-Dist: wordcloud
Requires-Dist: requests
Requires-Dist: chardet
Dynamic: license-file
